agin/__init__.py
agin/agin.py
agin-1.0.6.dist-info/METADATA
agin-1.0.6.dist-info/WHEEL
agin-1.0.6.dist-info/top_level.txt
agin-1.0.6.dist-info/RECORD
